blacknoise/__about__.py
blacknoise/__init__.py
blacknoise/_impl.py
blacknoise/compress.py
blacknoise-1.2.0.dist-info/METADATA
blacknoise-1.2.0.dist-info/WHEEL
blacknoise-1.2.0.dist-info/licenses/LICENSE.txt
blacknoise-1.2.0.dist-info/RECORD
