Metadata-Version: 2.3
Name: blacknoise
Version: 1.2.0
Summary: An ASGI app for static file serving inspired by whitenoise
Project-URL: Documentation, https://github.com/matthiask/blacknoise#readme
Project-URL: Issues, https://github.com/matthiask/blacknoise/issues
Project-URL: Source, https://github.com/matthiask/blacknoise
Author-email: Matthias Kestenholz <mk@feinheit.ch>
License: MIT
Classifier: Development Status :: 4 - Beta
Classifier: Programming Language :: Python
Classifier: Programming Language :: Python :: 3 :: Only
Classifier: Programming Language :: Python :: 3.9
Classifier: Programming Language :: Python :: 3.10
Classifier: Programming Language :: Python :: 3.11
Classifier: Programming Language :: Python :: 3.12
Classifier: Programming Language :: Python :: 3.13
Classifier: Programming Language :: Python :: Implementation :: CPython
Classifier: Programming Language :: Python :: Implementation :: PyPy
Requires-Python: >=3.9
Requires-Dist: starlette>=0.39
